main.py
tests/__init__.py
tests/test_basic.py
tests/test_code_cache.py
tests/test_data_extractor.py
tests/test_html_cleaner.py
tests/test_html_fetcher.py
tests/test_main.py
tests/test_universal_scraper.py
universal_scraper/__init__.py
universal_scraper/mcp_server.py
universal_scraper/scraper.py
universal_scraper/core/__init__.py
universal_scraper/core/code_cache.py
universal_scraper/core/data_extractor.py
universal_scraper/core/html_cleaner.py
universal_scraper/core/html_fetcher.py
universal_scraper/core/cleaning/__init__.py
universal_scraper/core/cleaning/attribute_cleaner.py
universal_scraper/core/cleaning/base_cleaner.py
universal_scraper/core/cleaning/content_optimizer.py
universal_scraper/core/cleaning/duplicate_finder.py
universal_scraper/core/cleaning/html_cleaner.py
universal_scraper/core/cleaning/noise_remover.py
universal_scraper/core/cleaning/structure_cleaner.py
universal_scraper/core/cleaning/url_replacer.py
universal_scraper/core/mcp/__init__.py
universal_scraper/core/mcp/exceptions.py
universal_scraper/core/mcp/server.py
universal_scraper/core/mcp/tools.py
universal_scraper/core/mcp/validators.py
universal_scraper-1.9.3.dist-info/licenses/LICENSE
universal_scraper-1.9.3.dist-info/METADATA
universal_scraper-1.9.3.dist-info/WHEEL
universal_scraper-1.9.3.dist-info/entry_points.txt
universal_scraper-1.9.3.dist-info/top_level.txt
universal_scraper-1.9.3.dist-info/RECORD
