Metadata-Version: 2.4
Name: universal-scraper
Version: 1.9.3
Summary: AI-powered web scraping with customizable field extraction using multiple AI providers
Home-page: https://github.com/WitesoAI/universal-scraper
Author: Witeso
Author-email: support@witeso.com
Project-URL: Bug Reports, https://github.com/WitesoAI/universal-scraper/issues
Project-URL: Source, https://github.com/WitesoAI/universal-scraper
Project-URL: Documentation, https://github.com/WitesoAI/universal-scraper/wiki
Keywords: web scraping,ai,data extraction,beautifulsoup,gemini,openai,anthropic,claude,gpt,litellm,automation,html parsing,structured data,caching,performance,multi-provider,mcp,model context protocol
Classifier: Development Status :: 4 - Beta
Classifier: Intended Audience :: Developers
Classifier: License :: OSI Approved :: MIT License
Classifier: Operating System :: OS Independent
Classifier: Programming Language :: Python :: 3
Classifier: Programming Language :: Python :: 3.7
Classifier: Programming Language :: Python :: 3.8
Classifier: Programming Language :: Python :: 3.9
Classifier: Programming Language :: Python :: 3.10
Classifier: Programming Language :: Python :: 3.11
Classifier: Programming Language :: Python :: 3.12
Classifier: Topic :: Internet :: WWW/HTTP :: Browsers
Classifier: Topic :: Software Development :: Libraries :: Python Modules
Classifier: Topic :: Text Processing :: Markup :: HTML
Requires-Python: >=3.9
License-File: LICENSE
Requires-Dist: google-generativeai>=0.3.0
Requires-Dist: litellm>=1.70.0
Requires-Dist: beautifulsoup4>=4.11.0
Requires-Dist: requests>=2.28.0
Requires-Dist: selenium>=4.0.0
Requires-Dist: lxml>=4.9.0
Requires-Dist: fake-useragent>=1.2.0
Requires-Dist: cloudscraper>=1.2.0
Provides-Extra: dev
Requires-Dist: pytest>=7.0.0; extra == "dev"
Requires-Dist: pytest-cov>=4.0.0; extra == "dev"
Requires-Dist: black>=22.0.0; extra == "dev"
Requires-Dist: flake8>=5.0.0; extra == "dev"
Requires-Dist: mypy>=1.0.0; extra == "dev"
Provides-Extra: mcp
Requires-Dist: mcp>=1.0.0; extra == "mcp"
Dynamic: author
Dynamic: author-email
Dynamic: classifier
Dynamic: description
Dynamic: description-content-type
Dynamic: home-page
Dynamic: keywords
Dynamic: license-file
Dynamic: project-url
Dynamic: provides-extra
Dynamic: requires-dist
Dynamic: requires-python
Dynamic: summary
